camp/__init__.py
camp/generators/__init__.py
camp/generators/base.py
camp/generators/create_agent_c.py
camp/generators/create_gen_h.py
camp/generators/create_impl_c.py
camp/generators/create_impl_h.py
camp/generators/create_mgr_c.py
camp/generators/create_sql.py
camp/generators/data/agent.c.jinja
camp/generators/data/agent.h.jinja
camp/generators/data/agent.pgsql.jinja
camp/generators/lib/__init__.py
camp/generators/lib/campch.py
camp/generators/lib/campch_roundtrip.py
camp/generators/lib/campsettings.py
camp/generators/lib/camputil.py
camp/tools/camp.py
dtnma_camp-2.0.0.dist-info/licenses/LICENSE
dtnma_camp-2.0.0.dist-info/METADATA
dtnma_camp-2.0.0.dist-info/WHEEL
dtnma_camp-2.0.0.dist-info/entry_points.txt
dtnma_camp-2.0.0.dist-info/top_level.txt
dtnma_camp-2.0.0.dist-info/RECORD
