Metadata-Version: 2.4
Name: dtnma-camp
Version: 2.0.0
Summary: C code generator for DTNMA tools
Author-email: JHU/APL <dtnma-support@jhuapl.edu>
License-Expression: Apache-2.0
Project-URL: Homepage, https://github.com/JHUAPL-DTNMA/dtnma-camp
Project-URL: Bug Tracker, https://github.com/JHUAPL-DTNMA/dtnma-camp/issues
Classifier: Development Status :: 5 - Production/Stable
Classifier: Programming Language :: Python :: 3
Classifier: Operating System :: OS Independent
Requires-Python: >=3.10
License-File: LICENSE
Requires-Dist: dtnma-ace
Requires-Dist: setuptools
Requires-Dist: jinja2
Provides-Extra: test
Requires-Dist: jinja2; extra == "test"
Requires-Dist: pytest; extra == "test"
Requires-Dist: pytest-cov; extra == "test"
Requires-Dist: coverage; extra == "test"
Requires-Dist: psycopg2-binary; extra == "test"
Provides-Extra: pylint
Requires-Dist: pylint; extra == "pylint"
Requires-Dist: pylint_junit; extra == "pylint"
Provides-Extra: flake8
Requires-Dist: flake8; extra == "flake8"
Requires-Dist: flake8_pyproject; extra == "flake8"
Requires-Dist: flake8_formatter_junit_xml; extra == "flake8"
Provides-Extra: docs
Requires-Dist: sphinx<6; extra == "docs"
Requires-Dist: sphinx_rtd_theme; extra == "docs"
Requires-Dist: sphinx-argparse; extra == "docs"
Dynamic: license-file
